odoo/addons/mail_save_as_template_security/README.rst
odoo/addons/mail_save_as_template_security/__init__.py
odoo/addons/mail_save_as_template_security/__manifest__.py
odoo/addons/mail_save_as_template_security/i18n/mail_save_as_template_security.pot
odoo/addons/mail_save_as_template_security/readme/CONFIGURE.md
odoo/addons/mail_save_as_template_security/readme/CONTRIBUTORS.md
odoo/addons/mail_save_as_template_security/readme/DESCRIPTION.md
odoo/addons/mail_save_as_template_security/readme/USAGE.md
odoo/addons/mail_save_as_template_security/security/mail_save_as_template_security.xml
odoo/addons/mail_save_as_template_security/static/description/icon.png
odoo/addons/mail_save_as_template_security/static/description/icon.svg
odoo/addons/mail_save_as_template_security/static/description/index.html
odoo/addons/mail_save_as_template_security/tests/__init__.py
odoo/addons/mail_save_as_template_security/tests/test_mail_save_as_template_security.py
odoo/addons/mail_save_as_template_security/wizard/mail_compose_message_view.xml
odoo_addon_mail_save_as_template_security-15.0.1.0.0.2.dist-info/METADATA
odoo_addon_mail_save_as_template_security-15.0.1.0.0.2.dist-info/WHEEL
odoo_addon_mail_save_as_template_security-15.0.1.0.0.2.dist-info/top_level.txt
odoo_addon_mail_save_as_template_security-15.0.1.0.0.2.dist-info/RECORD
