Metadata-Version: 2.1
Name: odoo-addon-mail_save_as_template_security
Version: 15.0.1.0.0.2
Summary: Restrict save as new template button from the send email wizard
Home-page: https://github.com/OCA/social
Author: Sygel, Odoo Community Association (OCA)
Author-email: support@odoo-community.org
License: AGPL-3
Classifier: Programming Language :: Python
Classifier: Framework :: Odoo
Classifier: Framework :: Odoo :: 15.0
Classifier: License :: OSI Approved :: GNU Affero General Public License v3
Requires-Python: >=3.8
Requires-Dist: odoo<15.1dev,>=15.0a
